package/__init__.py
package/enigma.py
package/utils.py
enigma_tpenha_junq-0.1.1.dist-info/METADATA
enigma_tpenha_junq-0.1.1.dist-info/WHEEL
enigma_tpenha_junq-0.1.1.dist-info/top_level.txt
enigma_tpenha_junq-0.1.1.dist-info/RECORD
