Metadata-Version: 2.1
Name: enigma_tpenha_junq
Version: 0.1.1
Summary: Enigma solving machine using numpy
Author: Thiago Penha
Author-email: tpenha30@gmail.com
Classifier: Programming Language :: Python :: 3
Classifier: License :: OSI Approved :: MIT License
Classifier: Operating System :: OS Independent
Requires-Dist: numpy
